{
  "notes": [
    {
      "id": 1,
      "title": "Note about felon",
      "timestamp": "07/29/2020",
      "author": "Suzie Police",
      "content": "I think Colonel Mustard did it."
    },
    {
      "title": "Test",
      "author": "Steve",
      "content": "No way",
      "timestamp": 1596205913084,
      "id": 2
    },
    {
      "title": "Suspicious emily",
      "author": "Steve",
      "content": "A strange character was in the parade today",
      "timestamp": 1596206055009,
      "id": 3
    },
    {
      "title": "jeofwnvdfojnvo",
      "author": "vnfdojvnwfojvn",
      "content": "vndfojvnfjnjfdn",
      "timestamp": 1596206093754,
      "id": 4
    }
  ]
}